twitch_helix/__init__.py
twitch_helix/client.py
twitch_helix/exceptions.py
twitch_helix/models.py
twitch_helix-0.1.1.dist-info/METADATA
twitch_helix-0.1.1.dist-info/WHEEL
twitch_helix-0.1.1.dist-info/top_level.txt
twitch_helix-0.1.1.dist-info/RECORD
