Metadata-Version: 2.1
Name: twitch-helix
Version: 0.1.1
Summary: python interface for the twitch helix api
Home-page: https://gitlab.com/henny022/twitch-helix
Author: Henny022
Author-email: hen.geheim22@gmail.com
License: Unlicense
Platform: UNKNOWN
Classifier: License :: OSI Approved :: The Unlicense (Unlicense)
Classifier: Programming Language :: Python :: 3
Classifier: Programming Language :: Python :: 3.7
Requires-Python: >=3.7
Requires-Dist: requests
